<?xml version="1.0" encoding="UTF-8" standalone="yes"?><profile><name>CheckmarxPHP</name><language>php</language><rules><rule><repositoryKey>checkmarx.rules.php</repositoryKey><key>checkmarx_1320</key></rule><rule><repositoryKey>checkmarx.rules.php</repositoryKey><key>checkmarx_2200</key></rule><rule><repositoryKey>checkmarx.rules.php</repositoryKey><key>checkmarx_5435</key></rule><rule><repositoryKey>checkmarx.rules.php</repositoryKey><key>checkmarx_2325</key></rule><rule><repositoryKey>checkmarx.rules.php</repositoryKey><key>checkmarx_2108</key></rule><rule><repositoryKey>checkmarx.rules.php</repositoryKey><key>checkmarx_4415</key></rule><rule><repositoryKey>checkmarx.rules.php</repositoryKey><key>checkmarx_2109</key></rule><rule><repositoryKey>checkmarx.rules.php</repositoryKey><key>checkmarx_4416</key></rule><rule><repositoryKey>checkmarx.rules.php</repositoryKey><key>checkmarx_2110</key></rule><rule><repositoryKey>checkmarx.rules.php</repositoryKey><key>checkmarx_2111</key></rule><rule><repositoryKey>checkmarx.rules.php</repositoryKey><key>checkmarx_2112</key></rule><rule><repositoryKey>checkmarx.rules.php</repositoryKey><key>checkmarx_4574</key></rule><rule><repositoryKey>checkmarx.rules.php</repositoryKey><key>checkmarx_2113</key></rule><rule><repositoryKey>checkmarx.rules.php</repositoryKey><key>checkmarx_1803</key></rule><rule><repositoryKey>checkmarx.rules.php</repositoryKey><key>checkmarx_3585</key></rule><rule><repositoryKey>checkmarx.rules.php</repositoryKey><key>checkmarx_1804</key></rule><rule><repositoryKey>checkmarx.rules.php</repositoryKey><key>checkmarx_1973</key></rule><rule><repositoryKey>checkmarx.rules.php</repositoryKey><key>checkmarx_1271</key></rule><rule><repositoryKey>checkmarx.rules.php</repositoryKey><key>checkmarx_4592</key></rule><rule><repositoryKey>checkmarx.rules.php</repositoryKey><key>checkmarx_2326</key></rule><rule><repositoryKey>checkmarx.rules.php</repositoryKey><key>checkmarx_1272</key></rule><rule><repositoryKey>checkmarx.rules.php</repositoryKey><key>checkmarx_1359</key></rule><rule><repositoryKey>checkmarx.rules.php</repositoryKey><key>checkmarx_2262</key></rule><rule><repositoryKey>checkmarx.rules.php</repositoryKey><key>checkmarx_5501</key></rule><rule><repositoryKey>checkmarx.rules.php</repositoryKey><key>checkmarx_3122</key></rule><rule><repositoryKey>checkmarx.rules.php</repositoryKey><key>checkmarx_3121</key></rule><rule><repositoryKey>checkmarx.rules.php</repositoryKey><key>checkmarx_1360</key></rule><rule><repositoryKey>checkmarx.rules.php</repositoryKey><key>checkmarx_3131</key></rule><rule><repositoryKey>checkmarx.rules.php</repositoryKey><key>checkmarx_3130</key></rule><rule><repositoryKey>checkmarx.rules.php</repositoryKey><key>checkmarx_3129</key></rule><rule><repositoryKey>checkmarx.rules.php</repositoryKey><key>checkmarx_3128</key></rule><rule><repositoryKey>checkmarx.rules.php</repositoryKey><key>checkmarx_3661</key></rule><rule><repositoryKey>checkmarx.rules.php</repositoryKey><key>checkmarx_3127</key></rule><rule><repositoryKey>checkmarx.rules.php</repositoryKey><key>checkmarx_1361</key></rule><rule><repositoryKey>checkmarx.rules.php</repositoryKey><key>checkmarx_1362</key></rule><rule><repositoryKey>checkmarx.rules.php</repositoryKey><key>checkmarx_1363</key></rule><rule><repositoryKey>checkmarx.rules.php</repositoryKey><key>checkmarx_1364</key></rule><rule><repositoryKey>checkmarx.rules.php</repositoryKey><key>checkmarx_3126</key></rule><rule><repositoryKey>checkmarx.rules.php</repositoryKey><key>checkmarx_3125</key></rule><rule><repositoryKey>checkmarx.rules.php</repositoryKey><key>checkmarx_1365</key></rule><rule><repositoryKey>checkmarx.rules.php</repositoryKey><key>checkmarx_1366</key></rule><rule><repositoryKey>checkmarx.rules.php</repositoryKey><key>checkmarx_3124</key></rule><rule><repositoryKey>checkmarx.rules.php</repositoryKey><key>checkmarx_3123</key></rule><rule><repositoryKey>checkmarx.rules.php</repositoryKey><key>checkmarx_2327</key></rule><rule><repositoryKey>checkmarx.rules.php</repositoryKey><key>checkmarx_3641</key></rule><rule><repositoryKey>checkmarx.rules.php</repositoryKey><key>checkmarx_1274</key></rule><rule><repositoryKey>checkmarx.rules.php</repositoryKey><key>checkmarx_1367</key></rule><rule><repositoryKey>checkmarx.rules.php</repositoryKey><key>checkmarx_2263</key></rule><rule><repositoryKey>checkmarx.rules.php</repositoryKey><key>checkmarx_5502</key></rule><rule><repositoryKey>checkmarx.rules.php</repositoryKey><key>checkmarx_3142</key></rule><rule><repositoryKey>checkmarx.rules.php</repositoryKey><key>checkmarx_3132</key></rule><rule><repositoryKey>checkmarx.rules.php</repositoryKey><key>checkmarx_1369</key></rule><rule><repositoryKey>checkmarx.rules.php</repositoryKey><key>checkmarx_3141</key></rule><rule><repositoryKey>checkmarx.rules.php</repositoryKey><key>checkmarx_3140</key></rule><rule><repositoryKey>checkmarx.rules.php</repositoryKey><key>checkmarx_3139</key></rule><rule><repositoryKey>checkmarx.rules.php</repositoryKey><key>checkmarx_3138</key></rule><rule><repositoryKey>checkmarx.rules.php</repositoryKey><key>checkmarx_3662</key></rule><rule><repositoryKey>checkmarx.rules.php</repositoryKey><key>checkmarx_3137</key></rule><rule><repositoryKey>checkmarx.rules.php</repositoryKey><key>checkmarx_1370</key></rule><rule><repositoryKey>checkmarx.rules.php</repositoryKey><key>checkmarx_1371</key></rule><rule><repositoryKey>checkmarx.rules.php</repositoryKey><key>checkmarx_1372</key></rule><rule><repositoryKey>checkmarx.rules.php</repositoryKey><key>checkmarx_1373</key></rule><rule><repositoryKey>checkmarx.rules.php</repositoryKey><key>checkmarx_3136</key></rule><rule><repositoryKey>checkmarx.rules.php</repositoryKey><key>checkmarx_3135</key></rule><rule><repositoryKey>checkmarx.rules.php</repositoryKey><key>checkmarx_1374</key></rule><rule><repositoryKey>checkmarx.rules.php</repositoryKey><key>checkmarx_1375</key></rule><rule><repositoryKey>checkmarx.rules.php</repositoryKey><key>checkmarx_3134</key></rule><rule><repositoryKey>checkmarx.rules.php</repositoryKey><key>checkmarx_3133</key></rule><rule><repositoryKey>checkmarx.rules.php</repositoryKey><key>checkmarx_2328</key></rule><rule><repositoryKey>checkmarx.rules.php</repositoryKey><key>checkmarx_5422</key></rule><rule><repositoryKey>checkmarx.rules.php</repositoryKey><key>checkmarx_5423</key></rule><rule><repositoryKey>checkmarx.rules.php</repositoryKey><key>checkmarx_1275</key></rule><rule><repositoryKey>checkmarx.rules.php</repositoryKey><key>checkmarx_2392</key></rule><rule><repositoryKey>checkmarx.rules.php</repositoryKey><key>checkmarx_2393</key></rule><rule><repositoryKey>checkmarx.rules.php</repositoryKey><key>checkmarx_2394</key></rule><rule><repositoryKey>checkmarx.rules.php</repositoryKey><key>checkmarx_2395</key></rule><rule><repositoryKey>checkmarx.rules.php</repositoryKey><key>checkmarx_1974</key></rule><rule><repositoryKey>checkmarx.rules.php</repositoryKey><key>checkmarx_1276</key></rule><rule><repositoryKey>checkmarx.rules.php</repositoryKey><key>checkmarx_1277</key></rule><rule><repositoryKey>checkmarx.rules.php</repositoryKey><key>checkmarx_3754</key></rule><rule><repositoryKey>checkmarx.rules.php</repositoryKey><key>checkmarx_1278</key></rule><rule><repositoryKey>checkmarx.rules.php</repositoryKey><key>checkmarx_2329</key></rule><rule><repositoryKey>checkmarx.rules.php</repositoryKey><key>checkmarx_2330</key></rule><rule><repositoryKey>checkmarx.rules.php</repositoryKey><key>checkmarx_3586</key></rule><rule><repositoryKey>checkmarx.rules.php</repositoryKey><key>checkmarx_2966</key></rule><rule><repositoryKey>checkmarx.rules.php</repositoryKey><key>checkmarx_3462</key></rule><rule><repositoryKey>checkmarx.rules.php</repositoryKey><key>checkmarx_5652</key></rule><rule><repositoryKey>checkmarx.rules.php</repositoryKey><key>checkmarx_3463</key></rule><rule><repositoryKey>checkmarx.rules.php</repositoryKey><key>checkmarx_3968</key></rule><rule><repositoryKey>checkmarx.rules.php</repositoryKey><key>checkmarx_2396</key></rule><rule><repositoryKey>checkmarx.rules.php</repositoryKey><key>checkmarx_1401</key></rule><rule><repositoryKey>checkmarx.rules.php</repositoryKey><key>checkmarx_5436</key></rule><rule><repositoryKey>checkmarx.rules.php</repositoryKey><key>checkmarx_1280</key></rule><rule><repositoryKey>checkmarx.rules.php</repositoryKey><key>checkmarx_4530</key></rule><rule><repositoryKey>checkmarx.rules.php</repositoryKey><key>checkmarx_1279</key></rule><rule><repositoryKey>checkmarx.rules.php</repositoryKey><key>checkmarx_1287</key></rule><rule><repositoryKey>checkmarx.rules.php</repositoryKey><key>checkmarx_1281</key></rule><rule><repositoryKey>checkmarx.rules.php</repositoryKey><key>checkmarx_1282</key></rule><rule><repositoryKey>checkmarx.rules.php</repositoryKey><key>checkmarx_1283</key></rule><rule><repositoryKey>checkmarx.rules.php</repositoryKey><key>checkmarx_1284</key></rule><rule><repositoryKey>checkmarx.rules.php</repositoryKey><key>checkmarx_1285</key></rule><rule><repositoryKey>checkmarx.rules.php</repositoryKey><key>checkmarx_1286</key></rule><rule><repositoryKey>checkmarx.rules.php</repositoryKey><key>checkmarx_2331</key></rule><rule><repositoryKey>checkmarx.rules.php</repositoryKey><key>checkmarx_2074</key></rule><rule><repositoryKey>checkmarx.rules.php</repositoryKey><key>checkmarx_2075</key></rule><rule><repositoryKey>checkmarx.rules.php</repositoryKey><key>checkmarx_4614</key></rule><rule><repositoryKey>checkmarx.rules.php</repositoryKey><key>checkmarx_2076</key></rule><rule><repositoryKey>checkmarx.rules.php</repositoryKey><key>checkmarx_2077</key></rule><rule><repositoryKey>checkmarx.rules.php</repositoryKey><key>checkmarx_2078</key></rule><rule><repositoryKey>checkmarx.rules.php</repositoryKey><key>checkmarx_2079</key></rule><rule><repositoryKey>checkmarx.rules.php</repositoryKey><key>checkmarx_1402</key></rule><rule><repositoryKey>checkmarx.rules.php</repositoryKey><key>checkmarx_1805</key></rule><rule><repositoryKey>checkmarx.rules.php</repositoryKey><key>checkmarx_2332</key></rule><rule><repositoryKey>checkmarx.rules.php</repositoryKey><key>checkmarx_1288</key></rule><rule><repositoryKey>checkmarx.rules.php</repositoryKey><key>checkmarx_1289</key></rule><rule><repositoryKey>checkmarx.rules.php</repositoryKey><key>checkmarx_5530</key></rule><rule><repositoryKey>checkmarx.rules.php</repositoryKey><key>checkmarx_4515</key></rule><rule><repositoryKey>checkmarx.rules.php</repositoryKey><key>checkmarx_1290</key></rule><rule><repositoryKey>checkmarx.rules.php</repositoryKey><key>checkmarx_2333</key></rule><rule><repositoryKey>checkmarx.rules.php</repositoryKey><key>checkmarx_1291</key></rule><rule><repositoryKey>checkmarx.rules.php</repositoryKey><key>checkmarx_4537</key></rule><rule><repositoryKey>checkmarx.rules.php</repositoryKey><key>checkmarx_1292</key></rule><rule><repositoryKey>checkmarx.rules.php</repositoryKey><key>checkmarx_1293</key></rule><rule><repositoryKey>checkmarx.rules.php</repositoryKey><key>checkmarx_1294</key></rule><rule><repositoryKey>checkmarx.rules.php</repositoryKey><key>checkmarx_1295</key></rule><rule><repositoryKey>checkmarx.rules.php</repositoryKey><key>checkmarx_1296</key></rule><rule><repositoryKey>checkmarx.rules.php</repositoryKey><key>checkmarx_1297</key></rule><rule><repositoryKey>checkmarx.rules.php</repositoryKey><key>checkmarx_1298</key></rule><rule><repositoryKey>checkmarx.rules.php</repositoryKey><key>checkmarx_1300</key></rule><rule><repositoryKey>checkmarx.rules.php</repositoryKey><key>checkmarx_3967</key></rule><rule><repositoryKey>checkmarx.rules.php</repositoryKey><key>checkmarx_1299</key></rule><rule><repositoryKey>checkmarx.rules.php</repositoryKey><key>checkmarx_2264</key></rule><rule><repositoryKey>checkmarx.rules.php</repositoryKey><key>checkmarx_5500</key></rule><rule><repositoryKey>checkmarx.rules.php</repositoryKey><key>checkmarx_3143</key></rule><rule><repositoryKey>checkmarx.rules.php</repositoryKey><key>checkmarx_1376</key></rule><rule><repositoryKey>checkmarx.rules.php</repositoryKey><key>checkmarx_3147</key></rule><rule><repositoryKey>checkmarx.rules.php</repositoryKey><key>checkmarx_3663</key></rule><rule><repositoryKey>checkmarx.rules.php</repositoryKey><key>checkmarx_1377</key></rule><rule><repositoryKey>checkmarx.rules.php</repositoryKey><key>checkmarx_1378</key></rule><rule><repositoryKey>checkmarx.rules.php</repositoryKey><key>checkmarx_5684</key></rule><rule><repositoryKey>checkmarx.rules.php</repositoryKey><key>checkmarx_4516</key></rule><rule><repositoryKey>checkmarx.rules.php</repositoryKey><key>checkmarx_1379</key></rule><rule><repositoryKey>checkmarx.rules.php</repositoryKey><key>checkmarx_1380</key></rule><rule><repositoryKey>checkmarx.rules.php</repositoryKey><key>checkmarx_3146</key></rule><rule><repositoryKey>checkmarx.rules.php</repositoryKey><key>checkmarx_1381</key></rule><rule><repositoryKey>checkmarx.rules.php</repositoryKey><key>checkmarx_1382</key></rule><rule><repositoryKey>checkmarx.rules.php</repositoryKey><key>checkmarx_3145</key></rule><rule><repositoryKey>checkmarx.rules.php</repositoryKey><key>checkmarx_4521</key></rule><rule><repositoryKey>checkmarx.rules.php</repositoryKey><key>checkmarx_4589</key></rule><rule><repositoryKey>checkmarx.rules.php</repositoryKey><key>checkmarx_2114</key></rule><rule><repositoryKey>checkmarx.rules.php</repositoryKey><key>checkmarx_2115</key></rule><rule><repositoryKey>checkmarx.rules.php</repositoryKey><key>checkmarx_5338</key></rule><rule><repositoryKey>checkmarx.rules.php</repositoryKey><key>checkmarx_2116</key></rule><rule><repositoryKey>checkmarx.rules.php</repositoryKey><key>checkmarx_2117</key></rule><rule><repositoryKey>checkmarx.rules.php</repositoryKey><key>checkmarx_2118</key></rule><rule><repositoryKey>checkmarx.rules.php</repositoryKey><key>checkmarx_3144</key></rule><rule><repositoryKey>checkmarx.rules.php</repositoryKey><key>checkmarx_1301</key></rule><rule><repositoryKey>checkmarx.rules.php</repositoryKey><key>checkmarx_2213</key></rule><rule><repositoryKey>checkmarx.rules.php</repositoryKey><key>checkmarx_2214</key></rule><rule><repositoryKey>checkmarx.rules.php</repositoryKey><key>checkmarx_2216</key></rule><rule><repositoryKey>checkmarx.rules.php</repositoryKey><key>checkmarx_2334</key></rule><rule><repositoryKey>checkmarx.rules.php</repositoryKey><key>checkmarx_1302</key></rule><rule><repositoryKey>checkmarx.rules.php</repositoryKey><key>checkmarx_4531</key></rule><rule><repositoryKey>checkmarx.rules.php</repositoryKey><key>checkmarx_5424</key></rule><rule><repositoryKey>checkmarx.rules.php</repositoryKey><key>checkmarx_4412</key></rule><rule><repositoryKey>checkmarx.rules.php</repositoryKey><key>checkmarx_2335</key></rule><rule><repositoryKey>checkmarx.rules.php</repositoryKey><key>checkmarx_1307</key></rule><rule><repositoryKey>checkmarx.rules.php</repositoryKey><key>checkmarx_1303</key></rule><rule><repositoryKey>checkmarx.rules.php</repositoryKey><key>checkmarx_1304</key></rule><rule><repositoryKey>checkmarx.rules.php</repositoryKey><key>checkmarx_1305</key></rule><rule><repositoryKey>checkmarx.rules.php</repositoryKey><key>checkmarx_1306</key></rule><rule><repositoryKey>checkmarx.rules.php</repositoryKey><key>checkmarx_1403</key></rule><rule><repositoryKey>checkmarx.rules.php</repositoryKey><key>checkmarx_3966</key></rule><rule><repositoryKey>checkmarx.rules.php</repositoryKey><key>checkmarx_4575</key></rule><rule><repositoryKey>checkmarx.rules.php</repositoryKey><key>checkmarx_3635</key></rule><rule><repositoryKey>checkmarx.rules.php</repositoryKey><key>checkmarx_1309</key></rule><rule><repositoryKey>checkmarx.rules.php</repositoryKey><key>checkmarx_1310</key></rule><rule><repositoryKey>checkmarx.rules.php</repositoryKey><key>checkmarx_3651</key></rule><rule><repositoryKey>checkmarx.rules.php</repositoryKey><key>checkmarx_3650</key></rule><rule><repositoryKey>checkmarx.rules.php</repositoryKey><key>checkmarx_3652</key></rule><rule><repositoryKey>checkmarx.rules.php</repositoryKey><key>checkmarx_3649</key></rule><rule><repositoryKey>checkmarx.rules.php</repositoryKey><key>checkmarx_1975</key></rule><rule><repositoryKey>checkmarx.rules.php</repositoryKey><key>checkmarx_1976</key></rule><rule><repositoryKey>checkmarx.rules.php</repositoryKey><key>checkmarx_1977</key></rule><rule><repositoryKey>checkmarx.rules.php</repositoryKey><key>checkmarx_1978</key></rule><rule><repositoryKey>checkmarx.rules.php</repositoryKey><key>checkmarx_1979</key></rule><rule><repositoryKey>checkmarx.rules.php</repositoryKey><key>checkmarx_2049</key></rule><rule><repositoryKey>checkmarx.rules.php</repositoryKey><key>checkmarx_2261</key></rule><rule><repositoryKey>checkmarx.rules.php</repositoryKey><key>checkmarx_2269</key></rule><rule><repositoryKey>checkmarx.rules.php</repositoryKey><key>checkmarx_2270</key></rule><rule><repositoryKey>checkmarx.rules.php</repositoryKey><key>checkmarx_2271</key></rule><rule><repositoryKey>checkmarx.rules.php</repositoryKey><key>checkmarx_1980</key></rule><rule><repositoryKey>checkmarx.rules.php</repositoryKey><key>checkmarx_1311</key></rule><rule><repositoryKey>checkmarx.rules.php</repositoryKey><key>checkmarx_1353</key></rule><rule><repositoryKey>checkmarx.rules.php</repositoryKey><key>checkmarx_1352</key></rule><rule><repositoryKey>checkmarx.rules.php</repositoryKey><key>checkmarx_2081</key></rule><rule><repositoryKey>checkmarx.rules.php</repositoryKey><key>checkmarx_1356</key></rule><rule><repositoryKey>checkmarx.rules.php</repositoryKey><key>checkmarx_1342</key></rule><rule><repositoryKey>checkmarx.rules.php</repositoryKey><key>checkmarx_4538</key></rule><rule><repositoryKey>checkmarx.rules.php</repositoryKey><key>checkmarx_1351</key></rule><rule><repositoryKey>checkmarx.rules.php</repositoryKey><key>checkmarx_1355</key></rule><rule><repositoryKey>checkmarx.rules.php</repositoryKey><key>checkmarx_2322</key></rule><rule><repositoryKey>checkmarx.rules.php</repositoryKey><key>checkmarx_2323</key></rule><rule><repositoryKey>checkmarx.rules.php</repositoryKey><key>checkmarx_2324</key></rule><rule><repositoryKey>checkmarx.rules.php</repositoryKey><key>checkmarx_1312</key></rule><rule><repositoryKey>checkmarx.rules.php</repositoryKey><key>checkmarx_1313</key></rule><rule><repositoryKey>checkmarx.rules.php</repositoryKey><key>checkmarx_3464</key></rule><rule><repositoryKey>checkmarx.rules.php</repositoryKey><key>checkmarx_2128</key></rule><rule><repositoryKey>checkmarx.rules.php</repositoryKey><key>checkmarx_3465</key></rule><rule><repositoryKey>checkmarx.rules.php</repositoryKey><key>checkmarx_1404</key></rule><rule><repositoryKey>checkmarx.rules.php</repositoryKey><key>checkmarx_1314</key></rule><rule><repositoryKey>checkmarx.rules.php</repositoryKey><key>checkmarx_1405</key></rule><rule><repositoryKey>checkmarx.rules.php</repositoryKey><key>checkmarx_1315</key></rule><rule><repositoryKey>checkmarx.rules.php</repositoryKey><key>checkmarx_1317</key></rule><rule><repositoryKey>checkmarx.rules.php</repositoryKey><key>checkmarx_1316</key></rule><rule><repositoryKey>checkmarx.rules.php</repositoryKey><key>checkmarx_1318</key></rule><rule><repositoryKey>checkmarx.rules.php</repositoryKey><key>checkmarx_1406</key></rule><rule><repositoryKey>checkmarx.rules.php</repositoryKey><key>checkmarx_1341</key></rule><rule><repositoryKey>checkmarx.rules.php</repositoryKey><key>checkmarx_4723</key></rule><rule><repositoryKey>checkmarx.rules.php</repositoryKey><key>checkmarx_1981</key></rule><rule><repositoryKey>checkmarx.rules.php</repositoryKey><key>checkmarx_1344</key></rule><rule><repositoryKey>checkmarx.rules.php</repositoryKey><key>checkmarx_1345</key></rule><rule><repositoryKey>checkmarx.rules.php</repositoryKey><key>checkmarx_2755</key></rule><rule><repositoryKey>checkmarx.rules.php</repositoryKey><key>checkmarx_1349</key></rule><rule><repositoryKey>checkmarx.rules.php</repositoryKey><key>checkmarx_1347</key></rule><rule><repositoryKey>checkmarx.rules.php</repositoryKey><key>checkmarx_1383</key></rule><rule><repositoryKey>checkmarx.rules.php</repositoryKey><key>checkmarx_1346</key></rule><rule><repositoryKey>checkmarx.rules.php</repositoryKey><key>checkmarx_3520</key></rule><rule><repositoryKey>checkmarx.rules.php</repositoryKey><key>checkmarx_2129</key></rule><rule><repositoryKey>checkmarx.rules.php</repositoryKey><key>checkmarx_2130</key></rule><rule><repositoryKey>checkmarx.rules.php</repositoryKey><key>checkmarx_4511</key></rule><rule><repositoryKey>checkmarx.rules.php</repositoryKey><key>checkmarx_1343</key></rule><rule><repositoryKey>checkmarx.rules.php</repositoryKey><key>checkmarx_2220</key></rule><rule><repositoryKey>checkmarx.rules.php</repositoryKey><key>checkmarx_1350</key></rule><rule><repositoryKey>checkmarx.rules.php</repositoryKey><key>checkmarx_1334</key></rule><rule><repositoryKey>checkmarx.rules.php</repositoryKey><key>checkmarx_1335</key></rule><rule><repositoryKey>checkmarx.rules.php</repositoryKey><key>checkmarx_5425</key></rule><rule><repositoryKey>checkmarx.rules.php</repositoryKey><key>checkmarx_1336</key></rule><rule><repositoryKey>checkmarx.rules.php</repositoryKey><key>checkmarx_2259</key></rule><rule><repositoryKey>checkmarx.rules.php</repositoryKey><key>checkmarx_3466</key></rule><rule><repositoryKey>checkmarx.rules.php</repositoryKey><key>checkmarx_2319</key></rule><rule><repositoryKey>checkmarx.rules.php</repositoryKey><key>checkmarx_2717</key></rule><rule><repositoryKey>checkmarx.rules.php</repositoryKey><key>checkmarx_2320</key></rule><rule><repositoryKey>checkmarx.rules.php</repositoryKey><key>checkmarx_4444</key></rule><rule><repositoryKey>checkmarx.rules.php</repositoryKey><key>checkmarx_3653</key></rule><rule><repositoryKey>checkmarx.rules.php</repositoryKey><key>checkmarx_2321</key></rule><rule><repositoryKey>checkmarx.rules.php</repositoryKey><key>checkmarx_1407</key></rule><rule><repositoryKey>checkmarx.rules.php</repositoryKey><key>checkmarx_5437</key></rule><rule><repositoryKey>checkmarx.rules.php</repositoryKey><key>checkmarx_3453</key></rule><rule><repositoryKey>checkmarx.rules.php</repositoryKey><key>checkmarx_1348</key></rule><rule><repositoryKey>checkmarx.rules.php</repositoryKey><key>checkmarx_1339</key></rule><rule><repositoryKey>checkmarx.rules.php</repositoryKey><key>checkmarx_1337</key></rule><rule><repositoryKey>checkmarx.rules.php</repositoryKey><key>checkmarx_2119</key></rule><rule><repositoryKey>checkmarx.rules.php</repositoryKey><key>checkmarx_4418</key></rule><rule><repositoryKey>checkmarx.rules.php</repositoryKey><key>checkmarx_3582</key></rule><rule><repositoryKey>checkmarx.rules.php</repositoryKey><key>checkmarx_2120</key></rule><rule><repositoryKey>checkmarx.rules.php</repositoryKey><key>checkmarx_1319</key></rule><rule><repositoryKey>checkmarx.rules.php</repositoryKey><key>checkmarx_3488</key></rule><rule><repositoryKey>checkmarx.rules.php</repositoryKey><key>checkmarx_3489</key></rule><rule><repositoryKey>checkmarx.rules.php</repositoryKey><key>checkmarx_3490</key></rule><rule><repositoryKey>checkmarx.rules.php</repositoryKey><key>checkmarx_3487</key></rule><rule><repositoryKey>checkmarx.rules.php</repositoryKey><key>checkmarx_3486</key></rule><rule><repositoryKey>checkmarx.rules.php</repositoryKey><key>checkmarx_3485</key></rule><rule><repositoryKey>checkmarx.rules.php</repositoryKey><key>checkmarx_3484</key></rule><rule><repositoryKey>checkmarx.rules.php</repositoryKey><key>checkmarx_2210</key></rule><rule><repositoryKey>checkmarx.rules.php</repositoryKey><key>checkmarx_1338</key></rule><rule><repositoryKey>checkmarx.rules.php</repositoryKey><key>checkmarx_1340</key></rule></rules></profile>